{
    "name" : "Finishes",
    "colorRanges" :
    [
        {
            "min" : null,
            "max" : -0.009,
            "color" : "violet"
        },
        {
            "min" : -0.009,
            "max" : -0.005,
            "color" : "red"
        },
        {
            "min" : -0.005,
            "max" : -0.000,
            "color" : "yellow"
        },
        {
            "min" : 0.000,
            "max" : 0.007,
            "color" : "green"
        },
        {
            "min" : 0.007,
            "max" : 0.009,
            "color" : "cyan"
        },
        {
            "min" : 0.009,
            "max" : null,
            "color" : "blue"
        }
    ]
}
